{
    "season": 2,
    "episode": 19,
    "title": "Michael's Birthday",
    "scenes": [
        [
            {
                "character": "Michael",
                "line": "So, Phil recruited me to sell these cards, and now I am recruiting you."
            },
            {
                "character": "Oscar",
                "line": "Who is this guy again?"
            },
            {
                "character": "Michael",
                "line": "Don't worry about Phil. He drives a corvette. He is doing just fine. Okay. Calling cards are... the wave of the future. These things sell themselves."
            },
            {
                "character": "Ryan",
                "line": "Who uses calling cards anymore?"
            },
            {
                "character": "Michael",
                "line": "You know what? That's a nice attitude, Ryan, I'm just helping you invest in your future, my friend."
            },
            {
                "character": "Oscar",
                "line": "This sounds like a get rich quick scheme."
            },
            {
                "character": "Michael",
                "line": "Yes! Thank you! You will get rich quick. We all will!"
            },
            {
                "character": "Toby",
                "line": "Didn't you lose a lot of money on that other investment, the one from the email?"
            },
            {
                "character": "Michael",
                "line": "You know what, Toby? When the son of the deposed king of Nigeria emails you directly, asking for help, you help! His father ran the freaking country, okay? ...Alright, so, raise your hand if you wanna get rich. [Jim and Dwight raise their hands] Alright."
            },
            {
                "character": "Jim",
                "line": "No, um. How is this not a pyramid scheme?"
            },
            {
                "character": "Michael",
                "line": "Alright, let me explain. Again. [draws on board] Phil has recruited me and another guy. Now, we are getting three people each. The more people that get involved, the more who are investing, the more money we're all going to make. It's not a pyramid scheme, it is a... it's not even a scheme per se, it's... [Jim draws a triangle around Michael's diagram] ... I have to go make a call."
            }
        ],
        [
            {
                "character": "Pam",
                "line": "Happy birthday Michael."
            },
            {
                "character": "Michael",
                "line": "Oh ho ho! What?"
            },
            {
                "character": "Pam",
                "line": "I said happy birthday."
            },
            {
                "character": "Michael",
                "line": "Thank you! That's really nice."
            }
        ],
        [
            {
                "character": "Michael",
                "line": "Today is my B-day, and people around here just go crazy for it. I don't know why. Oh! Fun fact. I share my birthday with Eva Longoria. So, I have a perfect ice-breaker if I ever meet Terry Hatcher."
            }
        ],
        [
            {
                "character": "Michael",
                "line": "What's up?"
            },
            {
                "character": "Jim",
                "line": "Hey. ...Oh, happy birthday."
            },
            {
                "character": "Michael",
                "line": "Ah, thank you sir."
            }
        ],
        [
            {
                "character": "Meredith",
                "line": "Did you hear anything yet?"
            },
            {
                "character": "Kevin",
                "line": "No. I'm still waiting."
            }
        ],
        [
            {
                "character": "Michael",
                "line": "[Dwight knocks on door] Yeah."
            },
            {
                "character": "Dwight",
                "line": "Yes. There he is, the birthday boy!"
            },
            {
                "character": "Michael",
                "line": "Ohh, god."
            },
            {
                "character": "Dwight",
                "line": "Birthday hug!"
            },
            {
                "character": "Michael",
                "line": "No no no, no, new suit, please."
            },
            {
                "character": "Dwight",
                "line": "That suit is amazing."
            },
            {
                "character": "Michael",
                "line": "Thank you very much. It is from Italy. [checks jacket] Actually--- no, Bulgaria."
            },
            {
                "character": "Dwight",
                "line": "Mmm. Maybe I should get one."
            },
            {
                "character": "Michael",
                "line": "Good luck. One of a kind."
            },
            {
                "character": "Dwight",
                "line": "Ebay. Hm. Question! May I be in charge of the party planning festivities?"
            },
            {
                "character": "Michael",
                "line": "Not necessary, the party planning committee is all over it. They've been working twenty-four seven all day yesterday."
            },
            {
                "character": "Dwight",
                "line": "Excellent. On my part, I did manage to reserve the..."
            },
            {
                "character": "Michael",
                "line": "Don't! Nope! Please, don't want to spoil it for anybody. Spoil the surprise."
            },
            {
                "character": "Dwight",
                "line": "Let's get the party started. [Begins 'raising the roof']"
            },
            {
                "character": "Michael",
                "line": "Let's get the party started. Not the way I taught you! [Michael joins in]"
            }
        ],
        [
            {
                "character": "Phyllis",
                "line": "When should we bring out the cake, one or one thirty?"
            },
            {
                "character": "Pam",
                "line": "One's good."
            },
            {
                "character": "Angela",
                "line": "One thirty. [Pam yawns] I'm sorry, are we boring you?"
            },
            {
                "character": "Dwight",
                "line": "Party planning committee, listen up. Michael would like trick candles for his birthday cake, so make that a priority."
            },
            {
                "character": "Phyllis",
                "line": "Where do we get those?"
            },
            {
                "character": "Dwight",
                "line": "Not my problem. Here is a list of things that Michael would like to be surprised by. [hands list to Pam]"
            },
            {
                "character": "Pam",
                "line": "Michael wants a strippergram?"
            },
            {
                "character": "Dwight",
                "line": "Yes, but he doesn't want to know when, or whom."
            },
            {
                "character": "Angela",
                "line": "No. This is a closed door meeting."
            }
        ],
        [
            {
                "character": "Michael",
                "line": "[answering phone] Yeah?"
            },
            {
                "character": "Pam",
                "line": "Michael, I have Jan on the line."
            },
            {
                "character": "Michael",
                "line": "Oh, great, put her through."
            },
            {
                "character": "Jan",
                "line": "Hello, Michael."
            },
            {
                "character": "Michael",
                "line": "Hey, you."
            },
            {
                "character": "Jan",
                "line": "I'm... returning your call, you said it was urgent."
            },
            {
                "character": "Michael",
                "line": "It is urgent, I just wanted to call and wish you a happy birthday."
            },
            {
                "character": "Jan",
                "line": "Well, today's not my birthday, so..."
            },
            {
                "character": "Michael",
                "line": "Really? 'Cause, I thought we had the same birthday."
            },
            {
                "character": "Jan",
                "line": "...Happy birthday, Michael."
            },
            {
                "character": "Michael",
                "line": "Thanks. [grins]"
            },
            {
                "character": "Jan",
                "line": "Am I on camera?"
            },
            {
                "character": "Michael",
                "line": "Nope. Totally private. You can say whatever is in your heart. [Jan hangs up]"
            },
            {
                "character": "Michael",
                "line": "[to Ryan, sitting across from Michael] ...You can take a five, if you want."
            }
        ],
        [
            {
                "character": "Michael",
                "line": "Somebody brought in donuts for my birthday!"
            },
            {
                "character": "Stanley",
                "line": "Mmhmm, happy birthday."
            },
            {
                "character": "Michael",
                "line": "Thanks."
            }
        ],
        [
            {
                "character": "Jim",
                "line": "Man, I'm so sorry. When do you find out?"
            },
            {
                "character": "Kevin",
                "line": "They said this afternoon. They're waiting on a second opinion."
            },
            {
                "character": "Jim",
                "line": "Oh, okay."
            },
            {
                "character": "Kelly",
                "line": "Second opinion on what?"
            },
            {
                "character": "Kevin",
                "line": "Um, I might have skin cancer."
            },
            {
                "character": "Kelly",
                "line": "Oh, no! I was watching Grey's Anatomy, and there was a lifeguard on it, and he had skin cancer too."
            },
            {
                "character": "Jim",
                "line": "Kelly, you know what..."
            }
        ],
        [
            {
                "character": "Kelly",
                "line": "I never really thought about death until Princess Diana died. That was the saddest funeral ever. That and my sister's."
            }
        ],
        [
            {
                "character": "Toby",
                "line": "Who brought in donuts?"
            },
            {
                "character": "Michael",
                "line": "Somebody got donuts for my birthday!"
            },
            {
                "character": "Toby",
                "line": "Happy birthday!"
            },
            {
                "character": "Michael",
                "line": "You didn't know it was my birthday."
            },
            {
                "character": "Toby",
                "line": "I... guess I forgot."
            },
            {
                "character": "Michael",
                "line": "Well, I guess I forgot to give you a donut [closes box]."
            },
            {
                "character": "Toby",
                "line": "Are you serious?"
            },
            {
                "character": "Michael",
                "line": "Mmm."
            }
        ],
        [
            {
                "character": "Oscar",
                "line": "Skin cancer is treatable."
            },
            {
                "character": "Kevin",
                "line": "Right."
            },
            {
                "character": "Oscar",
                "line": "It's going to be okay."
            },
            {
                "character": "Angela",
                "line": "You don't know it's going to be okay. Don't give him false hope. ...It's probably nothing, though."
            }
        ],
        [
            {
                "character": "Delivery Woman",
                "line": "Hi, delivery for Michael Scott."
            },
            {
                "character": "Michael",
                "line": "Here we go. Ohhhkay, this is great! [giggles] Thank you my friends, she is perfect! Ahhh, Dwight, may I have your chair please? And, um, some singles, if you will! Allllright. Nnnnn-dink! [puts single into delivery woman's pocket, giggles] Okay, um, alright. This has arms. Is that gonna be a... is that alright?"
            },
            {
                "character": "Delivery Woman",
                "line": "Uh... s-sure."
            },
            {
                "character": "Michael",
                "line": "[laughing] Okay. I'm so nervous."
            },
            {
                "character": "Pam",
                "line": "I can sign for it."
            },
            {
                "character": "Delivery Woman",
                "line": "Oh. Thanks."
            }
        ],
        [
            {
                "character": "Michael",
                "line": "When I was seven, my mother hired a pony and a cart to come to my house for all the kids... and... I got a really bad rash from the pony, and all the kids got to ride the pony and I had to go inside, and my mother was rubbing cream on me... for probably three hours, and I never came outside. And by the time I got out the pony was already in the truck. And around the corner. So that was my worst birthday."
            }
        ],
        [
            {
                "character": "Michael",
                "line": "[eating donuts while Dwight plays the recorder] Stop it. Stop! What is that?"
            },
            {
                "character": "Dwight",
                "line": "It's 'For the Longest Time,' by William Joel. It's you favorite song."
            },
            {
                "character": "Michael",
                "line": "Yeah, well, it's on the radio. My birthday blows. Nobody even signed my birthday poster. Probably my mother is the only one that cares enough to send me anything."
            },
            {
                "character": "Dwight",
                "line": "I probably care more than she does."
            },
            {
                "character": "Michael",
                "line": "You're making it worse. I bet Luke Perry's friends don't treat him like this [points to James Dean poster]."
            }
        ],
        [
            {
                "character": "Pam",
                "line": "When does he hear?"
            },
            {
                "character": "Jim",
                "line": "Sometime today."
            },
            {
                "character": "Pam",
                "line": "Ohh... poor Kevin."
            }
        ],
        [
            {
                "character": "Pam",
                "line": "If I knew I had a week to live, I would... probably go to Europe. And South America. And the Grand Canyon. And... I would want to see the Pacific Ocean. ...It would be a pretty busy week."
            }
        ],
        [
            {
                "character": "Dwight",
                "line": "Uh, that's a list price of four dollars and fifty cents. Unfortunately, this item is on [watch beeps] back... order... [hangs up] Michael! Michael! Michael Michael Michael! Come here, come here, come here! Come here!"
            },
            {
                "character": "Michael",
                "line": "What?"
            },
            {
                "character": "Dwight",
                "line": "Listen up everyone! It is 11:23 exactly, the exact moment when you emerged from your mother's vaginal canal, so... huh?! Right, have a seat. Please."
            },
            {
                "character": "Michael",
                "line": "[grinning] Ohhh, God."
            },
            {
                "character": "Dwight",
                "line": "There is a tradition that the Hebrews have of hoisting the birthday boy up on a chair."
            },
            {
                "character": "Michael",
                "line": "Ohhh, no."
            },
            {
                "character": "Dwight",
                "line": "So come help me celebrate Michael's birth moment. Kevin!"
            },
            {
                "character": "Oscar",
                "line": "...I'll do it."
            },
            {
                "character": "Michael",
                "line": "Ohh, no, no, no! I can't... Ryan, come on. Let's do this."
            },
            {
                "character": "Dwight",
                "line": "Creed! Come on. Stanley!"
            },
            {
                "character": "Pam",
                "line": "...I feel like we should go get Kevin something. Do you think we can sneak out of here?"
            },
            {
                "character": "Jim",
                "line": "Maybe, but... we're gonna need somebody to create a diversion, and..."
            },
            {
                "character": "Dwight",
                "line": "On three, we're going to hoist away! Ready?"
            },
            {
                "character": "Michael",
                "line": "Okay."
            },
            {
                "character": "Dwight",
                "line": "Happy birth moment, Michael."
            },
            {
                "character": "Michael",
                "line": "Thank you."
            },
            {
                "character": "Dwight",
                "line": "One. Two. Three! [Michael is raised until his head hits the ceiling]"
            },
            {
                "character": "Michael",
                "line": "Whoa whoa! Alright. Alright. Watch it... please."
            },
            {
                "character": "Dwight",
                "line": "Oscar..."
            },
            {
                "character": "Oscar",
                "line": "It wasn't me."
            }
        ],
        [
            {
                "character": "Dwight",
                "line": "Okay, that is not an eight foot sub."
            },
            {
                "character": "Delivery Boy",
                "line": "Uh, we don't make an eight foot sub. This is eight one foot subs."
            },
            {
                "character": "Dwight",
                "line": "F. Alright, what's the damage?"
            },
            {
                "character": "Delivery Boy",
                "line": "Uh, thirty-nine sixty."
            },
            {
                "character": "Dwight",
                "line": "[pulls out wallet] Thirty nine... sixty."
            }
        ],
        [
            {
                "character": "Dwight",
                "line": "Why tip someone for a job I'm capable of doing myself? I can deliver food. I can drive a taxi. I can, and do, cut my own hair. I did, however, tip my urologist, because... I am unable to pulverize my own kidney stones."
            }
        ],
        [
            {
                "character": "Dwight",
                "line": "Here they come."
            },
            {
                "character": "Michael",
                "line": "Get in here... everybody."
            },
            {
                "character": "Dwight",
                "line": "Come and get it!"
            },
            {
                "character": "Michael",
                "line": "Birthday party subs! My gift to you."
            },
            {
                "character": "Oscar",
                "line": "What is this?"
            },
            {
                "character": "Dwight",
                "line": "Uh, bologna, tomato and ketchup."
            },
            {
                "character": "Michael",
                "line": "The best."
            },
            {
                "character": "Stanley",
                "line": "These are all the same?"
            },
            {
                "character": "Michael",
                "line": "Yes."
            },
            {
                "character": "Angela",
                "line": "Bologna? I don't eat bologna."
            },
            {
                "character": "Michael",
                "line": "Well, then just have the tomato and ketchup. Still good."
            },
            {
                "character": "Angela",
                "line": "No."
            },
            {
                "character": "Michael",
                "line": "Just the bread, it's fresh baked."
            },
            {
                "character": "Angela",
                "line": "No."
            },
            {
                "character": "Michael",
                "line": "Mm-kay. Get whatever you want. [under breath] And choke on it."
            }
        ],
        [
            {
                "character": "Michael",
                "line": "When I was sixteen, I was supposed to go out on a date with a girl named Julie. But there was another Michael in the class that she apparently thought the date was with, so she went out with him, on my birthday. And, she got him a cake, at the restaurant. And it wasn't even his birthday, but I heard about it the next day in school. So... That was the worst birthday I think I ever had."
            }
        ],
        [
            {
                "character": "Jim",
                "line": "So. We got Kev some stuff. Um... a party pack of M&amp;M's, his favorite candy. A DVD of American Pie 2, which is his favorite movie, and, he lent it to Creed, so, I can guarantee you he won't get that back."
            },
            {
                "character": "Pam",
                "line": "Sixty-nine cup of noodles."
            },
            {
                "character": "Jim",
                "line": "Which we realize sounds crass, but, it... is his favorite number."
            },
            {
                "character": "Pam",
                "line": "And his favorite lunch."
            }
        ],
        [
            {
                "character": "Dwight",
                "line": "Hey temp, you know uh, we still got five feet of sandwich left [pulls ice cream cake out of freezer]."
            },
            {
                "character": "Ryan",
                "line": "[making peanut butter and jelly sandwich] Someone ate three feet of that thing?"
            },
            {
                "character": "Dwight",
                "line": "Hell, yeah. Save room for ice cream cake."
            },
            {
                "character": "Angela",
                "line": "[grabs cake] Oh. Thank you."
            },
            {
                "character": "Dwight",
                "line": "Oh. I got it."
            },
            {
                "character": "Angela",
                "line": "What are--- it's... the party planning committee."
            },
            {
                "character": "Dwight",
                "line": "[whispering] This is the most important day of the year. I can't risk anything."
            },
            {
                "character": "Angela",
                "line": "Fine."
            },
            {
                "character": "Dwight",
                "line": "What about that meeting... later... to discuss finances?"
            },
            {
                "character": "Angela",
                "line": "Yes... [whispering] but don't expect any cookie."
            },
            {
                "character": "Dwight",
                "line": "[whispering] But what if i'm hungry?"
            },
            {
                "character": "Angela",
                "line": "[whispering] No cookie."
            }
        ],
        [
            {
                "character": "Jim",
                "line": "[puts fabric softener into cart] ...What?"
            },
            {
                "character": "Pam",
                "line": "You use fabric softener?"
            },
            {
                "character": "Jim",
                "line": "Yeah, you don't?"
            },
            {
                "character": "Pam",
                "line": "No, I do."
            },
            {
                "character": "Jim",
                "line": "...Okay."
            }
        ],
        [
            {
                "character": "Office Staff",
                "line": "[singing] Happy birthday dear Michael, [Michael joins in, Kevin's phone rings] Happy birthday... [everyone but Dwight stops] ...tooo youuuu."
            },
            {
                "character": "Kevin",
                "line": "Hello? Hey."
            },
            {
                "character": "Michael",
                "line": "Kevin? Respect the birthday please."
            },
            {
                "character": "Kevin",
                "line": "No, um, no not yet. I will. Bye. [hangs up] It was just Stacy."
            },
            {
                "character": "Michael",
                "line": "Are you done? ...Good. Okay."
            },
            {
                "character": "Dwight",
                "line": "Here we go. Make a wish."
            },
            {
                "character": "Michael",
                "line": "Uhhh... blow out the candle. Okay. Mmmm... [blows out the candles]"
            },
            {
                "character": "Dwight",
                "line": "Yaoo yay! [claps]"
            },
            {
                "character": "Michael",
                "line": "... I asked for trick candles."
            },
            {
                "character": "Dwight",
                "line": "Pam was supposed to get 'em."
            },
            {
                "character": "Michael",
                "line": "Okay. Well, when she comes back we'll do it again. [notices Meredith hugging Kevin] Hello, what about the birthday boy? Haven't had a hug all day."
            },
            {
                "character": "Angela",
                "line": "No one cares about your birthday. Kevin's waiting to hear if he has skin cancer."
            },
            {
                "character": "Michael",
                "line": "... Aww, that... sucks, great. ... Wow, that's good timing. That's... that's, sorry, that's terrible. Terrible news. That's terrible... terrible news for both of us [takes cake into office and slams the door]."
            }
        ],
        [
            {
                "character": "Pam",
                "line": "[checking watch] We should probably head back."
            },
            {
                "character": "Jim",
                "line": "Yeah. Okay. Oh. I dare you to make an announcement."
            },
            {
                "character": "Pam",
                "line": "You dare me? How old are you?"
            },
            {
                "character": "Jim",
                "line": "Just... quit stalling."
            },
            {
                "character": "Pam",
                "line": "[over loudspeaker, imitating Darth Vader] Luke, this is your father. Come set the table for dinner."
            },
            {
                "character": "Jim",
                "line": "Such a dork."
            },
            {
                "character": "Pam",
                "line": "[loudspeaker] Jim Halpert? Price check on fabric softener, the kind that gives you..."
            },
            {
                "character": "Store Employee",
                "line": "Ma'am? Please don't touch that. That is not a toy."
            },
            {
                "character": "Pam",
                "line": "Oh I'm sorry. I'm sorry."
            },
            {
                "character": "Jim",
                "line": "How old are you?"
            },
            {
                "character": "Pam",
                "line": "I hate you."
            }
        ],
        [
            {
                "character": "Toby",
                "line": "[to Kevin] Honestly, is there any way you can get on your fiancee's plan? Our health plan is s... just... it's terrible."
            },
            {
                "character": "Michael",
                "line": "There you are. Good news. Did some research. It turns out that 98% of people with skin cancer fully recover."
            },
            {
                "character": "Kevin",
                "line": "Still scary."
            },
            {
                "character": "Michael",
                "line": "Yeah, but it's not brain cancer. And it shouldn't stop us from having fun. You know what they say the best medicine is."
            },
            {
                "character": "Kevin",
                "line": "Well the doctor said a combination of interferon and dicarbazine."
            },
            {
                "character": "Michael",
                "line": "And laughter... also."
            },
            {
                "character": "Toby",
                "line": "I don't really think people are in the laughing mood."
            },
            {
                "character": "Michael",
                "line": "Why are you here? I didn't even invite you to my birthday party."
            },
            {
                "character": "Toby",
                "line": "I work here."
            },
            {
                "character": "Michael",
                "line": "[mocking voice] Nyeh, I work here. [to Kevin] Alright, well, you know what, since Toby doesn't speak for everybody and I am your boss, I... think you should just go home. Take the rest of the afternoon off. Take a sick day."
            },
            {
                "character": "Kevin",
                "line": "If I go home now, I'll just drive myself crazy."
            },
            {
                "character": "Michael",
                "line": "Well, you're pretty much driving everyone else here crazy... crazy with worry."
            }
        ],
        [
            {
                "character": "Dwight",
                "line": "Where have you been? And don't say the bathroom, 'cause I kicked in all the stalls."
            },
            {
                "character": "Jim",
                "line": "Well that's an invasion of privacy, so, I'm going to tell Michael."
            },
            {
                "character": "Dwight",
                "line": "Please, don't."
            },
            {
                "character": "Jim",
                "line": "You... owe me."
            },
            {
                "character": "Michael",
                "line": "Excuse me, everyone. Attention please. Kevin, we're going to take you to a very special place, a place that will make you happy, and a place that is far, far away from the evil sun."
            },
            {
                "character": "Stanley",
                "line": "Is this trip related in any way to your... birthday?"
            },
            {
                "character": "Michael",
                "line": "How dare you sir. You are gross."
            }
        ],
        [
            {
                "character": "Michael",
                "line": "[sees 'Happy Birthday Michael Scott!' poster at skating rink] That should not be there."
            },
            {
                "character": "Dwight",
                "line": "I'll get someone to take it down."
            },
            {
                "character": "Michael",
                "line": "No, it's alright. It's already up. Just leave it. Where's Kevin? Come on! Let's get our skate on!"
            }
        ],
        [
            {
                "character": "Kelly",
                "line": "Don't be scared! You're good! You're good!"
            },
            {
                "character": "Ryan",
                "line": "Whoa whoa whoa whoa whoa whoa whoa."
            }
        ],
        [
            {
                "character": "Jim",
                "line": "Think you can let go?"
            },
            {
                "character": "Pam",
                "line": "No. [laughs]"
            },
            {
                "character": "Jim",
                "line": "Whoa whoa whoa whoa whoa. [Michael skates by]"
            },
            {
                "character": "Dwight",
                "line": "YEAH!"
            },
            {
                "character": "Pam",
                "line": "Who is that?"
            },
            {
                "character": "Jim",
                "line": "Is that Michael?"
            }
        ],
        [
            {
                "character": "Michael",
                "line": "Yeah, I've been pretty much skating my whole life. I thought about playing in the NHL, but, you're on the road so much. You got no time to spend with your wife and kids. And I really want a wife and kids."
            }
        ],
        [
            {
                "character": "Pam",
                "line": "I got it."
            },
            {
                "character": "Michael",
                "line": "Hey Pam, all this stuff with Kevin... um, it's pretty scary. And I'm thinking that uh, next time you're in the shower, you should check yourself out. You know, give yourself an exam. Those things are like ticking time bags. Alright? Think about it."
            },
            {
                "character": "Jim",
                "line": "...It's something to think about."
            }
        ],
        [
            {
                "character": "Kevin",
                "line": "I can't relax about it, you know?"
            },
            {
                "character": "Michael",
                "line": "Kevin. You heard anything yet?"
            },
            {
                "character": "Kevin",
                "line": "No, not yet."
            },
            {
                "character": "Michael",
                "line": "Okay. Well. Live strong."
            },
            {
                "character": "Kevin",
                "line": "Okay, Michael."
            },
            {
                "character": "Michael",
                "line": "Alright."
            },
            {
                "character": "Carol",
                "line": "Michael?"
            },
            {
                "character": "Michael",
                "line": "Yeah. Carol? She sold me my condo! Hey! What, is this place on the market? Or..."
            },
            {
                "character": "Carol",
                "line": "Uhh, no, I... don't just sell real estate. Uh, my daughter has a skating lesson."
            },
            {
                "character": "Michael",
                "line": "Oh, these... all your kids?"
            },
            {
                "character": "Carol",
                "line": "No just the front two."
            },
            {
                "character": "Michael",
                "line": "Oh, hey guys. Whats up? You wanna go for a ride? Is that okay?"
            },
            {
                "character": "Carol",
                "line": "Sure."
            },
            {
                "character": "Michael",
                "line": "Cool. Alright. Grab on. Here we go. Ready? Hang on tight. Alright. We are moving. We are reaaallly mooovin' now!"
            }
        ],
        [
            {
                "character": "Michael",
                "line": "Push. Good! That's great. You got it. [Kevin's phone rings] Excuse me."
            },
            {
                "character": "Kevin",
                "line": "Hello? Yeah okay. Alright. Okay, I will, thanks. [hangs up] It was negative."
            },
            {
                "character": "Michael",
                "line": "Oh... God... [stomps] God! [throws hockey stick and yellow paper bracelet down] We're gonna beat this, okay? We're gonna... come here [hugs Kevin]."
            }
        ],
        [
            {
                "character": "Michael",
                "line": "Well, apparently in the medicine community, negative means good. Which makes absolutely no sense. In the real world community, that would... be... chaos."
            }
        ],
        [
            {
                "character": "Kevin",
                "line": "This is awesome. Thanks, you guys."
            },
            {
                "character": "Michael",
                "line": "Okay, who's this from? Wowwwee, look at that! Jersey!"
            },
            {
                "character": "Dwight",
                "line": "Turn it around. Turn it around."
            },
            {
                "character": "Michael",
                "line": "Cool. Ohh. Great. From Dwight."
            },
            {
                "character": "Dwight",
                "line": "Number one!!"
            },
            {
                "character": "Michael",
                "line": "Thank you... Dwight. That's great. Thanks."
            },
            {
                "character": "Pam",
                "line": "Michael?"
            },
            {
                "character": "Michael",
                "line": "Yeah."
            },
            {
                "character": "Pam",
                "line": "This is from all of us."
            },
            {
                "character": "Michael",
                "line": "Oh! You didn't need to do that. ...Nightswept. This is... really amazing. Thank you. I love it."
            }
        ],
        [
            {
                "character": "Pam",
                "line": "Michael's birthday was actually pretty cool. It was a good day. I don't know... It was a good day."
            }
        ]
    ],
    "deleted_scenes": [
        [
            {
                "character": "Jim",
                "line": "Michael's birthday. It's pretty fun to watch, actually. He gets very excited, and then he eats a lot of cake. And then he runs around the office. Then he has a sugar crash in the afternoon. And then he falls asleep. And that's when we get our work done."
            }
        ],
        [
            {
                "character": "Dwight",
                "line": "Let's get the party started."
            },
            {
                "character": "Michael",
                "line": "That's not how I taught you, right? [singing] My hump, my hump, my lovely lady lump Check it out [Dwight imitating drumbeat]"
            }
        ],
        [
            {
                "character": "Dwight",
                "line": "Michael's birthday is hard for me because he gets very excited. But he's also under a lot of pressure, which builds up until he's ready to explode. As his right-hand man, it's my job to release that pressure so that he can enjoy himself, if only for a moment."
            }
        ],
        [
            {
                "character": "Michael",
                "line": "Okay, here's the thing about bosses and employees. A good boss will say, \"Hey, it's my birthday. Celebrate me.\" A great boss will say, \"Hey, it's my birthday. Celebrate yourselves, because you are the ones who made me great, and I will acknowledge your contributions with donuts.\""
            }
        ],
        [
            {
                "character": "Michael",
                "line": "Good. You know, Ryan, you didn't have to get me a present."
            },
            {
                "character": "Ryan",
                "line": "I won't."
            },
            {
                "character": "Michael",
                "line": "Good. Great."
            },
            {
                "character": "Ryan",
                "line": "Okay, good. I think I'm gonna go."
            },
            {
                "character": "Michael",
                "line": "No, I think you're gonna stay."
            }
        ],
        [
            {
                "character": "Michael",
                "line": "On my 20th birthday, my supposed best friend, Sam Ambrose, ditched me for his twin sister's Sweet Sixteen party. And that was my worst birthday. Until today."
            }
        ],
        [
            {
                "character": "Kevin",
                "line": "Can you please stop staring at me? [Dwight continues to stare and then walks away]"
            }
        ],
        [
            {
                "character": "Dwight",
                "line": "To think that a man's skin could turn on him. It's brilliant, 'cause you'd never expect it. Most people think of their skin as an ally. [scoffs] Makes me rethink having skin at all."
            }
        ],
        [
            {
                "character": "Michael",
                "line": "[knock on door] Mmm-hmm."
            },
            {
                "character": "Ryan",
                "line": "Hey. I got the information."
            },
            {
                "character": "Michael",
                "line": "Oh, good. Okay. Don't tell me, tell them."
            },
            {
                "character": "Ryan",
                "line": "[turns to camera] \"The survival rate for localized melanoma is 98%.\""
            },
            {
                "character": "Michael",
                "line": "Oh, my God. That's a piece of cake. That's a piece of cake. Oh, 2%. Jeez, that's good."
            },
            {
                "character": "Ryan",
                "line": "[looking at camera] \"There was 7,800 deaths from melanoma in 2005.\""
            },
            {
                "character": "Michael",
                "line": "Out of, like, 18 billion Americans, so, no worry."
            },
            {
                "character": "Ryan",
                "line": "\"For localized melanoma, the five-year survival rate is 98%. The survival rates for regional and...\""
            },
            {
                "character": "Michael",
                "line": "Those were probably misdiagnosed. I mean, anybody with a zit goes in and says, \"I have cancer.\""
            },
            {
                "character": "Ryan",
                "line": "\"The skin is the largest organ of the body.\""
            },
            {
                "character": "Michael",
                "line": "Untrue. The heart is bigger than the skin. If you stretched the heart out, it would cover more than the entire body."
            }
        ],
        [
            {
                "character": "Angela",
                "line": "I'm not afraid of dying. I know where I'm going. But if I were Kevin, I might be terrified. Gluttony."
            }
        ]
    ]
}